[
    {
        "BUFFER_POOL_TABLE:ingress_common_pool": {
            "size": "33958080",
            "type": "ingress",
            "mode": "dynamic",
            "xoff": "8356608"
        },
        "OP": "SET"
    },
    {
        "BUFFER_POOL_TABLE:egress_lossless_pool": {
            "size": "42349632",
            "type": "egress",
            "mode": "dynamic"
        },
        "OP": "SET"
    },
    {
        "BUFFER_POOL_TABLE:egress_lossy_pool": {
            "size": "26240448",
            "type": "egress",
            "mode": "dynamic"
        },
        "OP": "SET"
    },
    {
        "BUFFER_PROFILE_TABLE:ingress_lossless_profile": {
            "pool": "[BUFFER_POOL_TABLE:ingress_common_pool]",
            "xon": "0",
            "xoff": "56160",
            "size": "1248",
            "dynamic_th": "-3"
        },
        "OP": "SET"
    },
    {
        "BUFFER_PROFILE_TABLE:ingress_lossy_profile": {
            "pool":"[BUFFER_POOL_TABLE:ingress_common_pool]",
            "size":"0",
            "static_th":"11075584"
        },
        "OP": "SET"
    },
    {
        "BUFFER_PROFILE_TABLE:egress_lossless_profile": {
            "pool":"[BUFFER_POOL_TABLE:egress_lossless_pool]",
            "size":"1040",
            "dynamic_th":"3"
        },
        "OP": "SET"
    },
    {
        "BUFFER_PROFILE_TABLE:egress_lossy_profile": {
            "pool":"[BUFFER_POOL_TABLE:egress_lossy_pool]",
            "size":"1664",
            "dynamic_th":"-1"
        },
        "OP": "SET"
    },
    {
        "BUFFER_PG_TABLE:Ethernet0,Ethernet2,Ethernet4,Ethernet6,Ethernet8,Ethernet10,Ethernet12,Ethernet14,Ethernet16,Ethernet18,Ethernet20,Ethernet22,Ethernet24,Ethernet26,Ethernet28,Ethernet30,Ethernet32,Ethernet34,Ethernet36,Ethernet38,Ethernet40,Ethernet42,Ethernet44,Ethernet46,Ethernet48,Ethernet50,Ethernet52,Ethernet54,Ethernet56,Ethernet58,Ethernet60,Ethernet62,Ethernet64,Ethernet66,Ethernet68,Ethernet70,Ethernet72,Ethernet74,Ethernet76,Ethernet78,Ethernet80,Ethernet82,Ethernet84,Ethernet86,Ethernet88,Ethernet90,Ethernet92,Ethernet94,Ethernet96,Ethernet98,Ethernet100,Ethernet102,Ethernet104,Ethernet106,Ethernet108,Ethernet110,Ethernet112,Ethernet114,Ethernet116,Ethernet118,Ethernet120,Ethernet122,Ethernet124,Ethernet126,Ethernet128,Ethernet130,Ethernet132,Ethernet134,Ethernet136,Ethernet138,Ethernet140,Ethernet142,Ethernet144,Ethernet146,Ethernet148,Ethernet150,Ethernet152,Ethernet154,Ethernet156,Ethernet158,Ethernet160,Ethernet162,Ethernet164,Ethernet166,Ethernet168,Ethernet170,Ethernet172,Ethernet174,Ethernet176,Ethernet180,Ethernet184,Ethernet188,Ethernet192,Ethernet196,Ethernet200,Ethernet204,Ethernet208,Ethernet210,Ethernet212,Ethernet214,Ethernet216,Ethernet218,Ethernet220,Ethernet222,Ethernet224,Ethernet226,Ethernet228,Ethernet230,Ethernet232,Ethernet234,Ethernet236,Ethernet238,Ethernet240,Ethernet242,Ethernet244,Ethernet246:3-4": {
            "profile" : "[BUFFER_PROFILE_TABLE:ingress_lossless_profile]"
        },
        "OP": "SET"
    },
    {
        "BUFFER_PG_TABLE:Ethernet0,Ethernet2,Ethernet4,Ethernet6,Ethernet8,Ethernet10,Ethernet12,Ethernet14,Ethernet16,Ethernet18,Ethernet20,Ethernet22,Ethernet24,Ethernet26,Ethernet28,Ethernet30,Ethernet32,Ethernet34,Ethernet36,Ethernet38,Ethernet40,Ethernet42,Ethernet44,Ethernet46,Ethernet48,Ethernet50,Ethernet52,Ethernet54,Ethernet56,Ethernet58,Ethernet60,Ethernet62,Ethernet64,Ethernet66,Ethernet68,Ethernet70,Ethernet72,Ethernet74,Ethernet76,Ethernet78,Ethernet80,Ethernet82,Ethernet84,Ethernet86,Ethernet88,Ethernet90,Ethernet92,Ethernet94,Ethernet96,Ethernet98,Ethernet100,Ethernet102,Ethernet104,Ethernet106,Ethernet108,Ethernet110,Ethernet112,Ethernet114,Ethernet116,Ethernet118,Ethernet120,Ethernet122,Ethernet124,Ethernet126,Ethernet128,Ethernet130,Ethernet132,Ethernet134,Ethernet136,Ethernet138,Ethernet140,Ethernet142,Ethernet144,Ethernet146,Ethernet148,Ethernet150,Ethernet152,Ethernet154,Ethernet156,Ethernet158,Ethernet160,Ethernet162,Ethernet164,Ethernet166,Ethernet168,Ethernet170,Ethernet172,Ethernet174,Ethernet176,Ethernet180,Ethernet184,Ethernet188,Ethernet192,Ethernet196,Ethernet200,Ethernet204,Ethernet208,Ethernet210,Ethernet212,Ethernet214,Ethernet216,Ethernet218,Ethernet220,Ethernet222,Ethernet224,Ethernet226,Ethernet228,Ethernet230,Ethernet232,Ethernet234,Ethernet236,Ethernet238,Ethernet240,Ethernet242,Ethernet244,Ethernet246:0-1": {
            "profile" : "[BUFFER_PROFILE_TABLE:ingress_lossy_profile]"
        },
        "OP": "SET"
    },
    {
        "BUFFER_QUEUE_TABLE:Ethernet0,Ethernet2,Ethernet4,Ethernet6,Ethernet8,Ethernet10,Ethernet12,Ethernet14,Ethernet16,Ethernet18,Ethernet20,Ethernet22,Ethernet24,Ethernet26,Ethernet28,Ethernet30,Ethernet32,Ethernet34,Ethernet36,Ethernet38,Ethernet40,Ethernet42,Ethernet44,Ethernet46,Ethernet48,Ethernet50,Ethernet52,Ethernet54,Ethernet56,Ethernet58,Ethernet60,Ethernet62,Ethernet64,Ethernet66,Ethernet68,Ethernet70,Ethernet72,Ethernet74,Ethernet76,Ethernet78,Ethernet80,Ethernet82,Ethernet84,Ethernet86,Ethernet88,Ethernet90,Ethernet92,Ethernet94,Ethernet96,Ethernet98,Ethernet100,Ethernet102,Ethernet104,Ethernet106,Ethernet108,Ethernet110,Ethernet112,Ethernet114,Ethernet116,Ethernet118,Ethernet120,Ethernet122,Ethernet124,Ethernet126,Ethernet128,Ethernet130,Ethernet132,Ethernet134,Ethernet136,Ethernet138,Ethernet140,Ethernet142,Ethernet144,Ethernet146,Ethernet148,Ethernet150,Ethernet152,Ethernet154,Ethernet156,Ethernet158,Ethernet160,Ethernet162,Ethernet164,Ethernet166,Ethernet168,Ethernet170,Ethernet172,Ethernet174,Ethernet176,Ethernet180,Ethernet184,Ethernet188,Ethernet192,Ethernet196,Ethernet200,Ethernet204,Ethernet208,Ethernet210,Ethernet212,Ethernet214,Ethernet216,Ethernet218,Ethernet220,Ethernet222,Ethernet224,Ethernet226,Ethernet228,Ethernet230,Ethernet232,Ethernet234,Ethernet236,Ethernet238,Ethernet240,Ethernet242,Ethernet244,Ethernet246:3-4": {
            "profile" : "[BUFFER_PROFILE_TABLE:egress_lossless_profile]"
        },
        "OP": "SET"
    },
    {
        "BUFFER_QUEUE_TABLE:Ethernet0,Ethernet2,Ethernet4,Ethernet6,Ethernet8,Ethernet10,Ethernet12,Ethernet14,Ethernet16,Ethernet18,Ethernet20,Ethernet22,Ethernet24,Ethernet26,Ethernet28,Ethernet30,Ethernet32,Ethernet34,Ethernet36,Ethernet38,Ethernet40,Ethernet42,Ethernet44,Ethernet46,Ethernet48,Ethernet50,Ethernet52,Ethernet54,Ethernet56,Ethernet58,Ethernet60,Ethernet62,Ethernet64,Ethernet66,Ethernet68,Ethernet70,Ethernet72,Ethernet74,Ethernet76,Ethernet78,Ethernet80,Ethernet82,Ethernet84,Ethernet86,Ethernet88,Ethernet90,Ethernet92,Ethernet94,Ethernet96,Ethernet98,Ethernet100,Ethernet102,Ethernet104,Ethernet106,Ethernet108,Ethernet110,Ethernet112,Ethernet114,Ethernet116,Ethernet118,Ethernet120,Ethernet122,Ethernet124,Ethernet126,Ethernet128,Ethernet130,Ethernet132,Ethernet134,Ethernet136,Ethernet138,Ethernet140,Ethernet142,Ethernet144,Ethernet146,Ethernet148,Ethernet150,Ethernet152,Ethernet154,Ethernet156,Ethernet158,Ethernet160,Ethernet162,Ethernet164,Ethernet166,Ethernet168,Ethernet170,Ethernet172,Ethernet174,Ethernet176,Ethernet180,Ethernet184,Ethernet188,Ethernet192,Ethernet196,Ethernet200,Ethernet204,Ethernet208,Ethernet210,Ethernet212,Ethernet214,Ethernet216,Ethernet218,Ethernet220,Ethernet222,Ethernet224,Ethernet226,Ethernet228,Ethernet230,Ethernet232,Ethernet234,Ethernet236,Ethernet238,Ethernet240,Ethernet242,Ethernet244,Ethernet246:0-1": {
            "profile" : "[BUFFER_PROFILE_TABLE:egress_lossy_profile]"
        },
        "OP": "SET"
    }
]
